{"is_source_file": false, "format": "", "description": "", "external_files": [], "external_methods": [], "published": [], "classes": [], "methods": [], "calls": [], "search-terms": [], "state": 2, "file_id": 18, "knowledge_revision": 186, "git_revision": "27bde6c3671a302ddab7215859937064730eedff", "hash": "3028ba9f8aacbda27f126ab841ac6e88", "format-version": 4, "code-base-name": "frontend_react_js", "filename": "frontend_react_js/index.html", "revision_history": [{"186": "27bde6c3671a302ddab7215859937064730eedff"}]}