{"is_source_file": true, "format": "TypeScript (TSX)", "description": "This file defines a React component named BehaviorCountBarChart that renders an interactive bar chart visualizing behavior counts. The component includes toggles for hiding/showing behaviors and handles user interactions via clicks on bars and legend buttons.", "external_files": ["recharts", "@/lib/behaviorPalette"], "external_methods": ["getBehaviorColor"], "published": ["BehaviorCountBarChart"], "classes": [], "methods": [{"name": "BehaviorCountBarChart", "description": "React functional component rendering an interactive bar chart with toggleable behavior types."}], "calls": ["setHidden", "useMemo", "map", "toggleType", "getBehaviorColor", "onBarClick"], "search-terms": ["BehaviorCountBarChart", "recharts", "toggle behavior visibility", "interactive bar chart", "behavior palette"], "state": 2, "file_id": 37, "knowledge_revision": 373, "git_revision": "0bb9c397662232d4febe4b85f10e13d32930dffa", "revision_history": [{"78": ""}, {"242": "27bde6c3671a302ddab7215859937064730eedff"}, {"249": "3c28f04cf9bed476187774fa6d88fd9eb01f2699"}, {"355": "0bb9c397662232d4febe4b85f10e13d32930dffa"}, {"373": "0bb9c397662232d4febe4b85f10e13d32930dffa"}], "ctags": [], "hash": "85205c7d8c50456a55573104a99848d9", "format-version": 4, "code-base-name": "frontend_react_js", "filename": "frontend_react_js/src/components/charts/BehaviorCountBarChart.tsx"}