{"is_source_file": true, "format": "TypeScript", "description": "This file defines and exports a constant array representing various animal behavior types used within the animal behavior analytics platform.", "external_files": [], "external_methods": [], "published": ["BEHAVIOR_TYPES"], "classes": [], "methods": [], "calls": [], "search-terms": ["BEHAVIOR_TYPES", "behavior", "constants", "animal behavior"], "state": 2, "file_id": 70, "knowledge_revision": 146, "git_revision": "", "ctags": [{"_type": "tag", "name": "BEHAVIOR_TYPES", "path": "/home/kavia/workspace/code-generation/animal-behavior-analytics-platform-40568-40577/frontend_react_js/src/lib/constants.ts", "pattern": "/^export const BEHAVIOR_TYPES = ['Foraging', 'Resting', 'Grooming', 'Walking', 'Alert'];$/", "language": "TypeScript", "kind": "constant"}], "hash": "0080c7c8fff85433fcfd2b583121b837", "format-version": 4, "code-base-name": "frontend_react_js", "filename": "frontend_react_js/src/lib/constants.ts", "revision_history": [{"146": ""}]}