{"is_source_file": true, "format": "TypeScript (TSX)", "description": "React component 'DurationStackedBar' that renders a horizontal stacked bar chart for behavior durations using Recharts, with coloring based on behavior palette.", "external_files": ["react", "recharts", "@/lib/behaviorPalette"], "external_methods": ["getBehaviorColor"], "published": ["DurationStackedBar"], "classes": [], "methods": [{"name": "DurationStackedBar", "description": "React functional component rendering a responsive, horizontal stacked bar chart for behavior durations, using provided data and key labels."}], "calls": ["getBehaviorColor"], "search-terms": ["DurationStackedBar", "recharts", "vertical bar chart", "behavior palette", "React component"], "state": 2, "file_id": 38, "knowledge_revision": 252, "git_revision": "27bde6c3671a302ddab7215859937064730eedff", "revision_history": [{"79": ""}, {"252": "27bde6c3671a302ddab7215859937064730eedff"}], "ctags": [], "hash": "133ca2aca1d52b0a8eb0097a1b03e7a2", "format-version": 4, "code-base-name": "frontend_react_js", "filename": "frontend_react_js/src/components/charts/DurationStackedBar.tsx"}